<runStats artifactCreator="align-inductive_BPIC2018_control_k3" machineName="cl5n015.ib0.hpc.qut.edu.au" runnerVersion="0.9.1.4">
   <inputLogFileName>BPIC2018_control.xes</inputLogFileName>
   <outputModelFileName>converted from efficient tree imported from (osmodel_align-inductive_BPIC2018_control_k3.pnml)</outputModelFileName>
   <runDate>2022-12-12 16:03:24.645 AEST</runDate>
   <taskRunStats class="java.util.LinkedList">
      <taskStats taskName="tpmlogparser" runState="RUNNING">
         <duration>0</duration>
         <start>1670825004645</start>
         <errorMessage></errorMessage>
         <measureStats measure="LOG_TRACE_COUNT">
            <number class="java.lang.Integer">35046</number>
         </measureStats>
         <measureStats measure="LOG_EVENT_COUNT">
            <number class="java.lang.Integer">128918</number>
         </measureStats>
      </taskStats>
      <taskStats taskName="calculate Naive SPN entity count" runState="SUCCESS">
         <duration>0</duration>
         <start>1670825008167</start>
         <errorMessage></errorMessage>
         <measureStats measure="MODEL_ENTITY_COUNT">
            <number class="java.lang.Integer">20</number>
         </measureStats>
         <measureStats measure="MODEL_EDGE_COUNT">
            <number class="java.lang.Integer">24</number>
         </measureStats>
         <measureStats measure="NORMALIZED_PETRI_NET_EDGE_SIMPLICITY">
            <number class="java.lang.Double">0.9998138351510263</number>
         </measureStats>
      </taskStats>
      <taskStats taskName="calculate Earth Movers Similarity Tuned" runState="SUCCESS">
         <duration>102</duration>
         <start>1670825008191</start>
         <errorMessage></errorMessage>
         <measureStats measure="EARTH_MOVERS_LIGHT_COVERAGE">
            <number class="java.lang.Double">0.9691669107632069</number>
         </measureStats>
      </taskStats>
      <taskStats taskName="calculate Alpha Precision Unrestricted alpha-sig 0.0" runState="SUCCESS">
         <duration>54</duration>
         <start>1670825008307</start>
         <errorMessage></errorMessage>
         <measureStats measure="ALPHA_PRECISION_UNRESTRICTED">
            <number class="java.lang.Double">0.995</number>
         </measureStats>
      </taskStats>
   </taskRunStats>
   <errorMessage></errorMessage>
   <runState>RUNNING</runState>
</runStats>