<runStats artifactCreator="ToothpasteMinerHP" machineName="SEF-PA00143522" runnerVersion="27-11-2022">
   <inputLogFileName>BPIC2018_reference_k2.xes</inputLogFileName>
   <outputModelFileName>var\osmodel_tmh_BPIC2018_reference_k2.pnml</outputModelFileName>
   <runDate>2022-11-27 23:34:51.377 AEST</runDate>
   <taskRunStats class="java.util.LinkedList">
      <taskStats taskName="spmlogparser" runState="SUCCESS">
         <duration>551</duration>
         <start>1669556091377</start>
         <errorMessage></errorMessage>
         <measureStats measure="LOG_EVENT_COUNT">
            <number class="java.lang.Integer">25614</number>
         </measureStats>
         <measureStats measure="LOG_TRACE_COUNT">
            <number class="java.lang.Integer">8761</number>
         </measureStats>
      </taskStats>
      <taskStats taskName="miner" runState="SUCCESS">
         <duration>11222</duration>
         <start>1669556091929</start>
         <errorMessage></errorMessage>
      </taskStats>
      <taskStats taskName="calculate Naive SPN entity count" runState="SUCCESS">
         <duration>0</duration>
         <start>1669556105763</start>
         <errorMessage></errorMessage>
         <measureStats measure="NORMALIZED_PETRI_NET_EDGE_SIMPLICITY">
            <number class="java.lang.Double">0.9863609869827084</number>
         </measureStats>
         <measureStats measure="MODEL_ENTITY_COUNT">
            <number class="java.lang.Integer">1270</number>
         </measureStats>
         <measureStats measure="MODEL_EDGE_COUNT">
            <number class="java.lang.Integer">1404</number>
         </measureStats>
      </taskStats>
      <taskStats taskName="calculate Earth Movers Similarity Tuned" runState="SUCCESS">
         <duration>69</duration>
         <start>1669556105768</start>
         <errorMessage></errorMessage>
         <measureStats measure="EARTH_MOVERS_LIGHT_COVERAGE">
            <number class="java.lang.Double">0.6538203777563147</number>
         </measureStats>
      </taskStats>
      <taskStats taskName="calculate Earth Movers Similarity" runState="SUCCESS">
         <duration>82</duration>
         <start>1669556105839</start>
         <errorMessage></errorMessage>
         <measureStats measure="EARTH_MOVERS_SIMILARITY">
            <number class="java.lang.Double">0.6566581805685209</number>
         </measureStats>
      </taskStats>
      <taskStats taskName="visualize" runState="SUCCESS">
         <duration>162</duration>
         <start>1669556103313</start>
         <errorMessage></errorMessage>
      </taskStats>
   </taskRunStats>
   <errorMessage></errorMessage>
   <runState>SUCCESS</runState>
</runStats>