<runStats artifactCreator="msaprh-split_BPIC2018_reference_k4" machineName="cl4n091.ib0.hpc.qut.edu.au" runnerVersion="0.9.1.4">
   <inputLogFileName>BPIC2018_reference.xes</inputLogFileName>
   <outputModelFileName>net1 imported from (omodel_split_BPIC2018_reference_k4.pnml) imported from (osmodel_msaprh-split_BPIC2018_reference_k4.pnml)</outputModelFileName>
   <runDate>2022-12-06 14:12:18.363 AEST</runDate>
   <taskRunStats class="java.util.LinkedList">
      <taskStats taskName="tpmlogparser" runState="RUNNING">
         <duration>0</duration>
         <start>1670299938363</start>
         <errorMessage></errorMessage>
         <measureStats measure="LOG_EVENT_COUNT">
            <number class="java.lang.Integer">102803</number>
         </measureStats>
         <measureStats measure="LOG_TRACE_COUNT">
            <number class="java.lang.Integer">35041</number>
         </measureStats>
      </taskStats>
       <!-- separate run var/mrun_split_BPIC2018_reference_k4.xml merged into common file -->
      <taskStats taskName="miner" runState="SUCCESS">
         <duration>1421</duration>
         <start>1670224689585</start>
         <errorMessage></errorMessage>
      </taskStats>
      <taskStats taskName="calculate Naive SPN entity count" runState="SUCCESS">
         <duration>0</duration>
         <start>1670299943166</start>
         <errorMessage></errorMessage>
         <measureStats measure="NORMALIZED_PETRI_NET_EDGE_SIMPLICITY">
            <number class="java.lang.Double">0.9996887250372071</number>
         </measureStats>
         <measureStats measure="MODEL_EDGE_COUNT">
            <number class="java.lang.Integer">32</number>
         </measureStats>
         <measureStats measure="MODEL_ENTITY_COUNT">
            <number class="java.lang.Integer">26</number>
         </measureStats>
      </taskStats>
      <taskStats taskName="calculate Earth Movers Similarity Tuned" runState="SUCCESS">
         <duration>317</duration>
         <start>1670299943182</start>
         <errorMessage></errorMessage>
         <measureStats measure="EARTH_MOVERS_LIGHT_COVERAGE">
            <number class="java.lang.Double">0.9589058681229927</number>
         </measureStats>
      </taskStats>
      <taskStats taskName="calculate Alpha Precision Unrestricted alpha-sig 0.0" runState="SUCCESS">
         <duration>382</duration>
         <start>1670299943508</start>
         <errorMessage></errorMessage>
         <measureStats measure="ALPHA_PRECISION_UNRESTRICTED">
            <number class="java.lang.Double">0.71</number>
         </measureStats>
      </taskStats>
   </taskRunStats>
   <errorMessage></errorMessage>
   <runState>RUNNING</runState>
</runStats>
